fbs_build_utils/__init__.py
fbs_build_utils/__main__.py
fbs_build_utils/cli.py
fbs_build_utils/generate_icons.py
fbs_build_utils/main.py
fbs_build_utils/os_cmd.py
fbs_build_utils/rename_installer.py
fbs_build_utils-1.1.3.dist-info/METADATA
fbs_build_utils-1.1.3.dist-info/WHEEL
fbs_build_utils-1.1.3.dist-info/entry_points.txt
fbs_build_utils-1.1.3.dist-info/RECORD
