Metadata-Version: 2.4
Name: fbs-build-utils
Version: 1.1.3
Summary: An utility to facilitate the building of fman build system based projects
Requires-Python: >=3.10
Requires-Dist: click>=8.1.8
Requires-Dist: distro>=1.9.0
Requires-Dist: fbs>=0.8.4
Requires-Dist: gitpython>=3.1.44
Requires-Dist: pillow>=11.1.0
Requires-Dist: pyinstaller>=6.12.0
Requires-Dist: qt-build-utils>=1.0.5
